{
  "recipe": {
    "description": "browned butter in chocolate chip cookies\nOR crisco baking lard instead of butter, but then dont freeze\nMexican vanilla",
    "notes": "Tags: American, Dessert, Normal, chocolate",
    "title": "Chocolate Chip Cookies",
    "yield_detail": null,
    "yield_phrase": null,
    "yield_unit_name": null,
    "yield_units": 1
  },
  "schema_v": 1,
  "steps": [
    {
      "ingredient_lines": [
        {
          "confidence": 0.72,
          "ingredient_id": "44f8009a-9900-4fe2-9f7c-a3bd8681b6d1",
          "input_item": "Firstly",
          "input_qty": null,
          "input_unit_id": null,
          "is_optional": false,
          "note": "I still add the salt, however I will also 1/2 Cup salted and 1/2 Cup unsalted butter.",
          "preparation": null,
          "quantity_kind": "unquantified",
          "raw_text": "Firstly, I still add the salt, however I will also 1/2 Cup salted and 1/2 Cup unsalted butter."
        },
        {
          "confidence": 0.727,
          "ingredient_id": "b327ee27-b057-4b54-9eb9-9f421725ad14",
          "input_item": "vanilla extract",
          "input_qty": null,
          "input_unit_id": null,
          "is_optional": false,
          "note": "With my mixer and the pastry paddle attachment, I cream together the egg, the salt, and sugars until they're a single consistency, with a low",
          "preparation": "the butter which has been softened to room temperature, medium-low speed. Be sure to scrape off the bottom and sides a few times to aid in this.",
          "quantity_kind": "unquantified",
          "raw_text": "With my mixer and the pastry paddle attachment, I cream together the egg, the butter which has been softened to room temperature, the salt, vanilla extract, and sugars until they're a single consistency, with a low/ medium-low speed. Be sure to scrape off the bottom and sides a few times to aid in this."
        },
        {
          "confidence": 0.749,
          "ingredient_id": "c14d4c6b-f594-4140-ad57-400236bb16e1",
          "input_item": "A few tips with this",
          "input_qty": null,
          "input_unit_id": null,
          "is_optional": false,
          "note": null,
          "preparation": null,
          "quantity_kind": "unquantified",
          "raw_text": "A few tips with this:"
        },
        {
          "confidence": 0.936,
          "ingredient_id": "69b814f9-a5b7-4b8c-8ba8-848966bff514",
          "input_item": null,
          "input_qty": null,
          "input_unit_id": null,
          "is_optional": false,
          "note": "Use only dark brown sugar and when measuring it and make sure it's packed.",
          "preparation": null,
          "quantity_kind": "unquantified",
          "raw_text": "Use only dark brown sugar and when measuring it and make sure it's packed."
        },
        {
          "confidence": 0.857,
          "ingredient_id": "edc19744-fac8-4456-9911-a93a7831ba92",
          "input_item": "Use a fine grind of salt",
          "input_qty": null,
          "input_unit_id": null,
          "is_optional": false,
          "note": "like table salt. No kosher.",
          "preparation": null,
          "quantity_kind": "unquantified",
          "raw_text": "Use a fine grind of salt, like table salt. No kosher."
        },
        {
          "confidence": 0.924,
          "ingredient_id": "24195559-6d1e-4a0c-9a73-6511ef1735b5",
          "input_item": "Sift your white sugar.",
          "input_qty": null,
          "input_unit_id": null,
          "is_optional": false,
          "note": "Where I am is humid and we can get chunks of",
          "preparation": null,
          "quantity_kind": "unquantified",
          "raw_text": "Sift your white sugar. Where I am is humid and we can get chunks of solidified sugar."
        },
        {
          "confidence": 0.946,
          "ingredient_id": "16167376-1fac-4907-ba05-1c7e9e7cbae8",
          "input_item": null,
          "input_qty": null,
          "input_unit_id": null,
          "is_optional": false,
          "note": "While that's churning away, I will sift together my baking soda and flour. This I feel helps the wet mix with the dry better.",
          "preparation": null,
          "quantity_kind": "unquantified",
          "raw_text": "While that's churning away, I will sift together my baking soda and flour. This I feel helps the wet mix with the dry better."
        },
        {
          "confidence": 0.714,
          "ingredient_id": "ac3a43f6-23fc-4542-ba75-a021fdf68744",
          "input_item": "When the butter",
          "input_qty": null,
          "input_unit_id": null,
          "is_optional": false,
          "note": "take off the paddle attachment, scrape it off, add the flour to your mixing bowl, along with your chocolate chips and if you so desire, nuts. Attach your dough hook and with the speed on the lowest setting possible (mine says \"STIR\"), combine your wet and dry",
          "preparation": "are well creamed, stopping to scrape off the sides and the bottom of your bowl often.",
          "quantity_kind": "unquantified",
          "raw_text": "When the butter and sugars are well creamed, take off the paddle attachment, scrape it off, add the flour to your mixing bowl, along with your chocolate chips and if you so desire, nuts. Attach your dough hook and with the speed on the lowest setting possible (mine says \"STIR\"), combine your wet and dry, stopping to scrape off the sides and the bottom of your bowl often."
        },
        {
          "confidence": 0.563,
          "ingredient_id": "4141ff9d-0c01-46e6-bd22-854ec37ae2ca",
          "input_item": "Another tip if adding nuts",
          "input_qty": null,
          "input_unit_id": null,
          "is_optional": false,
          "note": null,
          "preparation": null,
          "quantity_kind": "unquantified",
          "raw_text": "Another tip if adding nuts:"
        },
        {
          "confidence": 0.968,
          "ingredient_id": "0d5c2ee9-5a67-4202-9dfa-ea585731143d",
          "input_item": null,
          "input_qty": null,
          "input_unit_id": null,
          "is_optional": false,
          "note": "Pecans I feel get chewy when baked like this and peanuts can taste rancid or even take over in the taste department. If you want a subtle nutty flavor with some crunch, I use only walnuts.",
          "preparation": null,
          "quantity_kind": "unquantified",
          "raw_text": "Pecans I feel get chewy when baked like this and peanuts can taste rancid or even take over in the taste department. If you want a subtle nutty flavor with some crunch, I use only walnuts."
        },
        {
          "confidence": 0.973,
          "ingredient_id": "c7bd223e-e727-4a25-8f3b-7b539ea5bc52",
          "input_item": "When your mixing your dough",
          "input_qty": null,
          "input_unit_id": null,
          "is_optional": false,
          "note": "the second it appears everything is combined stop. You don't want to overwork the gluten in the flour.",
          "preparation": null,
          "quantity_kind": "unquantified",
          "raw_text": "When your mixing your dough, the second it appears everything is combined stop. You don't want to overwork the gluten in the flour."
        },
        {
          "confidence": 0.885,
          "ingredient_id": "de6c68d2-81e9-400e-9e38-3e2db541fd3e",
          "input_item": null,
          "input_qty": null,
          "input_unit_id": null,
          "is_optional": false,
          "note": "Once your dough is done STOP. Don't bake it immediately. What you will do is this",
          "preparation": null,
          "quantity_kind": "unquantified",
          "raw_text": "Once your dough is done STOP. Don't bake it immediately. What you will do is this:"
        },
        {
          "confidence": 0.984,
          "ingredient_id": "764d97c9-a3d8-4189-886e-938d3c9da366",
          "input_item": null,
          "input_qty": null,
          "input_unit_id": null,
          "is_optional": false,
          "note": "Roll your dough into balls. The size I found that works best is 1/8 Cup Measure. You can either buy a #1$8th measure (and if you're an avid baker it comes in handy), or you can achieve this by simple measuring out two table spoons of dough and combining them into one ball.",
          "preparation": null,
          "quantity_kind": "unquantified",
          "raw_text": "Roll your dough into balls. The size I found that works best is 1/8 Cup Measure. You can either buy a 1/8th measure (and if you're an avid baker it comes in handy), or you can achieve this by simple measuring out two table spoons of dough and combining them into one ball."
        },
        {
          "confidence": 0.977,
          "ingredient_id": "ea3e39bf-2d20-4f06-954a-67f1f2d4669b",
          "input_item": null,
          "input_qty": null,
          "input_unit_id": null,
          "is_optional": false,
          "note": "When your done rolling a ball, place it directly onto a cookie/baking sheet. You're going to place these guys into a freezer so you only need to space them 1/4 inch apart.",
          "preparation": null,
          "quantity_kind": "unquantified",
          "raw_text": "When your done rolling a ball, place it directly onto a cookie/baking sheet. You're going to place these guys into a freezer so you only need to space them 1/4 inch apart."
        },
        {
          "confidence": 0.991,
          "ingredient_id": "a33372b6-9fe4-4d1b-8786-617ebb32cff3",
          "input_item": null,
          "input_qty": null,
          "input_unit_id": null,
          "is_optional": false,
          "note": "Freeze your dough balls for about 30 minutes and from there you can transfer them into a gallon size Zip-Lock bag or a container with a seal-able lid. I have a large glass container with a silicone cover I keep my balls in.",
          "preparation": null,
          "quantity_kind": "unquantified",
          "raw_text": "Freeze your dough balls for about 30 minutes and from there you can transfer them into a gallon size Zip-Lock bag or a container with a seal-able lid. I have a large glass container with a silicone cover I keep my balls in."
        },
        {
          "confidence": 0.622,
          "ingredient_id": "270ea1cf-0595-475c-86d3-a4f950dda06e",
          "input_item": "Once transferred keep them in your freezer",
          "input_qty": null,
          "input_unit_id": null,
          "is_optional": false,
          "note": "and freeze them overnight.",
          "preparation": null,
          "quantity_kind": "unquantified",
          "raw_text": "Once transferred keep them in your freezer and freeze them overnight."
        },
        {
          "confidence": 0.97,
          "ingredient_id": "c0c58aa8-696d-4705-9ebd-5ef6ebc4d761",
          "input_item": null,
          "input_qty": null,
          "input_unit_id": null,
          "is_optional": false,
          "note": "When your ready to bake, preheat your oven to 350F. Place your dough balls ~ 2\" apart directly onto the sheet. Now... I can't give you time here. I watch my dough. What I look for is this",
          "preparation": null,
          "quantity_kind": "unquantified",
          "raw_text": "When your ready to bake, preheat your oven to 350F. Place your dough balls ~2\" apart directly onto the sheet. Now... I can't give you time here. I watch my dough. What I look for is this:"
        },
        {
          "confidence": 0.793,
          "ingredient_id": "335b7ec5-46ca-4499-b17a-1f7e87c13c1f",
          "input_item": null,
          "input_qty": null,
          "input_unit_id": null,
          "is_optional": false,
          "note": "The bottoms looking golden brown and muy delicioso and",
          "preparation": null,
          "quantity_kind": "unquantified",
          "raw_text": "The bottoms looking golden brown and muy delicioso and"
        },
        {
          "confidence": 0.77,
          "ingredient_id": "9e5263ae-ff6b-4631-bfe9-a4a86a5ab8c4",
          "input_item": "pull them out.",
          "input_qty": null,
          "input_unit_id": null,
          "is_optional": false,
          "note": "They will spread out and puff up and look like muffin tops. When the tops start looking dry (not as shiny as they were)",
          "preparation": null,
          "quantity_kind": "unquantified",
          "raw_text": "They will spread out and puff up and look like muffin tops. When the tops start looking dry (not as shiny as they were) pull them out."
        },
        {
          "confidence": 0.974,
          "ingredient_id": "84a21679-6b79-41d5-93fc-3ffb4a3da424",
          "input_item": null,
          "input_qty": null,
          "input_unit_id": null,
          "is_optional": false,
          "note": "Now, they're technically not done, and will need to keep cooking and the residual heat is going to do just that. However, you don't want them to cool too rapidly or too slowly.",
          "preparation": null,
          "quantity_kind": "unquantified",
          "raw_text": "Now, they're technically not done, and will need to keep cooking and the residual heat is going to do just that. However, you don't want them to cool too rapidly or too slowly."
        },
        {
          "confidence": 0.855,
          "ingredient_id": "337aa872-8352-4deb-abcf-9d352ab0371b",
          "input_item": null,
          "input_qty": null,
          "input_unit_id": null,
          "is_optional": false,
          "note": "What I will do is I will take a bath towel (something CLEAN and somewhat fluffy - like cotton)",
          "preparation": "fold it until it's roughly the same size as your pan and place the pan onto the towel.",
          "quantity_kind": "unquantified",
          "raw_text": "What I will do is I will take a bath towel (something CLEAN and somewhat fluffy - like cotton), fold it until it's roughly the same size as your pan and place the pan onto the towel."
        },
        {
          "confidence": 0.335,
          "ingredient_id": "0f06b5b4-75fe-4a5a-b0ff-f7425f56518d",
          "input_item": "Some more tips",
          "input_qty": null,
          "input_unit_id": null,
          "is_optional": false,
          "note": null,
          "preparation": null,
          "quantity_kind": "unquantified",
          "raw_text": "Some more tips:"
        },
        {
          "confidence": 0.992,
          "ingredient_id": "35fd308c-8851-4997-81ee-cf67d90f6329",
          "input_item": null,
          "input_qty": null,
          "input_unit_id": null,
          "is_optional": false,
          "note": "Never leave your dough balls out. Keep them in the freezer. If you're working in batches, which I usually am, I will take my dough out, place them onto the sheet and whatever's still in my container it goes right back into the freezer and the sheet pan will go immediately into the oven.",
          "preparation": null,
          "quantity_kind": "unquantified",
          "raw_text": "Never leave your dough balls out. Keep them in the freezer. If you're working in batches, which I usually am, I will take my dough out, place them onto the sheet and whatever's still in my container it goes right back into the freezer and the sheet pan will go immediately into the oven."
        },
        {
          "confidence": 0.967,
          "ingredient_id": "eb4a0006-7ea2-45e9-acac-4a902833edce",
          "input_item": null,
          "input_qty": null,
          "input_unit_id": null,
          "is_optional": false,
          "note": "Make sure your oven is preheated. Also, I will put my oven rack about a third to three quarters up towards the top, not in the middle position. However, all ovens are different and I would experiment to see what positioning works best for you.",
          "preparation": null,
          "quantity_kind": "unquantified",
          "raw_text": "Make sure your oven is preheated. Also, I will put my oven rack about a third to three quarters up towards the top, not in the middle position. However, all ovens are different and I would experiment to see what positioning works best for you."
        },
        {
          "confidence": 0.976,
          "ingredient_id": "d1ebab7b-6e5a-40f7-b9e5-273988d32e1e",
          "input_item": null,
          "input_qty": null,
          "input_unit_id": null,
          "is_optional": false,
          "note": "Never use a warm or hot pan. This can cause the butter in the dough to start melting too early. Only use the pan when its cold or sufficiently cooled off. Drives my family up a wall because I'll have four pans I'm rotating, but its worth it in the end because COOKIES!",
          "preparation": null,
          "quantity_kind": "unquantified",
          "raw_text": "Never use a warm or hot pan. This can cause the butter in the dough to start melting too early. Only use the pan when its cold or sufficiently cooled off. Drives my family up a wall because I'll have four pans I'm rotating, but its worth it in the end because COOKIES!"
        },
        {
          "confidence": 0.81,
          "ingredient_id": "08c3ee81-2a7b-408b-9825-a5f98d1a692c",
          "input_item": "minutes on the pan.",
          "input_qty": 8.0,
          "input_unit_id": null,
          "is_optional": false,
          "note": "Let your cookies cool for, At that point you should be able to pick them up by hand, I recommend using a fish turner., and boy do I love it.",
          "preparation": "however if you want to use a spatula, I bought one specifically for helping me out with cookies because it's light and thin",
          "quantity_kind": "quantified",
          "raw_text": "Let your cookies cool for about 6-10 minutes on the pan. At that point you should be able to pick them up by hand, however if you want to use a spatula, I recommend using a fish turner. I bought one specifically for helping me out with cookies because it's light and thin, and boy do I love it."
        }
      ],
      "instruction": "See original recipe for details."
    }
  ]
}