{
  "recipe": {
    "description": null,
    "notes": "Tags: Main, Normal, beef tenderloin, red wine, walnut",
    "title": "Beef tenderloin with Marinaded Walnut sauce",
    "yield_detail": null,
    "yield_phrase": null,
    "yield_unit_name": null,
    "yield_units": 1
  },
  "schema_v": 1,
  "steps": [
    {
      "ingredient_lines": [
        {
          "ingredient_id": "f73c17f3-e648-4438-9af2-1cadf9cacf97",
          "input_qty": null,
          "input_unit_id": null,
          "is_optional": false,
          "note": null,
          "quantity_kind": "unquantified",
          "raw_text": "INGREDIENTS"
        },
        {
          "ingredient_id": "19d7f217-3f85-48c4-ab7f-95fe0530cb3c",
          "input_qty": null,
          "input_unit_id": null,
          "is_optional": false,
          "note": null,
          "quantity_kind": "unquantified",
          "raw_text": "2 tablespoons butter"
        },
        {
          "ingredient_id": "5b62e883-f481-4c19-836c-9aee854ba462",
          "input_qty": null,
          "input_unit_id": null,
          "is_optional": false,
          "note": null,
          "quantity_kind": "unquantified",
          "raw_text": "2 cloves garlic minced"
        },
        {
          "ingredient_id": "7d8d723a-f8fb-4c2e-a695-a8ac4ca058bc",
          "input_qty": null,
          "input_unit_id": null,
          "is_optional": false,
          "note": null,
          "quantity_kind": "unquantified",
          "raw_text": "1/2 onion finely chopped"
        },
        {
          "ingredient_id": "8e0b1a2f-6a3e-4f42-a202-1cb55d3153c2",
          "input_qty": null,
          "input_unit_id": null,
          "is_optional": false,
          "note": null,
          "quantity_kind": "unquantified",
          "raw_text": "2 tablespoons all-purpose flour"
        },
        {
          "ingredient_id": "c52bef0e-7bb9-43af-87e6-ac529a70f086",
          "input_qty": null,
          "input_unit_id": null,
          "is_optional": false,
          "note": null,
          "quantity_kind": "unquantified",
          "raw_text": "1/2 cup dry red wine"
        },
        {
          "ingredient_id": "d704e490-395c-4657-ae1a-605d9b31093d",
          "input_qty": null,
          "input_unit_id": null,
          "is_optional": false,
          "note": null,
          "quantity_kind": "unquantified",
          "raw_text": "1 1/2 cup beef stock"
        },
        {
          "ingredient_id": "de9dae9a-504b-4208-9350-a3c8a1bfad8d",
          "input_qty": null,
          "input_unit_id": null,
          "is_optional": false,
          "note": null,
          "quantity_kind": "unquantified",
          "raw_text": "2 lbs beef tenderloin"
        },
        {
          "ingredient_id": "778dea07-388e-4cfa-a84a-6d63448acedd",
          "input_qty": null,
          "input_unit_id": null,
          "is_optional": false,
          "note": null,
          "quantity_kind": "unquantified",
          "raw_text": "1/2 teaspoon each salt and pepper"
        },
        {
          "ingredient_id": "6650f0d7-e2d4-499b-936a-20e031d0eece",
          "input_qty": null,
          "input_unit_id": null,
          "is_optional": false,
          "note": null,
          "quantity_kind": "unquantified",
          "raw_text": "Marinated Walnuts:"
        },
        {
          "ingredient_id": "99a80212-371c-4470-89b4-3a72dcbd0a93",
          "input_qty": null,
          "input_unit_id": null,
          "is_optional": false,
          "note": null,
          "quantity_kind": "unquantified",
          "raw_text": "1 cup walnut halves lightly toasted"
        },
        {
          "ingredient_id": "a38f8469-e19f-4ebb-8216-8a433a380466",
          "input_qty": null,
          "input_unit_id": null,
          "is_optional": false,
          "note": null,
          "quantity_kind": "unquantified",
          "raw_text": "1 teaspoon cocoa powder"
        },
        {
          "ingredient_id": "461b014b-af71-4351-9b8c-5a65ad64b058",
          "input_qty": null,
          "input_unit_id": null,
          "is_optional": false,
          "note": null,
          "quantity_kind": "unquantified",
          "raw_text": "1 teaspoon grated lemon rind"
        },
        {
          "ingredient_id": "84eb956f-9b57-469f-96ac-176ae51c8361",
          "input_qty": null,
          "input_unit_id": null,
          "is_optional": false,
          "note": null,
          "quantity_kind": "unquantified",
          "raw_text": "1/2 teaspoon pepper"
        },
        {
          "ingredient_id": "b76e154c-f742-4fbd-8248-5014b58ba2c0",
          "input_qty": null,
          "input_unit_id": null,
          "is_optional": false,
          "note": null,
          "quantity_kind": "unquantified",
          "raw_text": "1/2 teaspoon ground allspice"
        },
        {
          "ingredient_id": "8ce5bd25-3a3d-45f9-8053-29b01101ac26",
          "input_qty": null,
          "input_unit_id": null,
          "is_optional": false,
          "note": null,
          "quantity_kind": "unquantified",
          "raw_text": "1/2 teaspoon ground cloves"
        },
        {
          "ingredient_id": "85523d9d-bb67-480c-8643-5d23f19c7b67",
          "input_qty": null,
          "input_unit_id": null,
          "is_optional": false,
          "note": null,
          "quantity_kind": "unquantified",
          "raw_text": "1/2 teaspoon ground Szechuan pepper (optional)"
        },
        {
          "ingredient_id": "555fd37a-962e-4985-bc0c-593e2693bf24",
          "input_qty": null,
          "input_unit_id": null,
          "is_optional": false,
          "note": null,
          "quantity_kind": "unquantified",
          "raw_text": "1/4 teaspoon vanilla"
        },
        {
          "ingredient_id": "c388a26e-3174-4462-b780-35e0a1c8223f",
          "input_qty": null,
          "input_unit_id": null,
          "is_optional": false,
          "note": null,
          "quantity_kind": "unquantified",
          "raw_text": "1 pinch salt"
        },
        {
          "ingredient_id": "c36905b9-7dc6-4682-aeb3-1874ac9d4214",
          "input_qty": null,
          "input_unit_id": null,
          "is_optional": false,
          "note": null,
          "quantity_kind": "unquantified",
          "raw_text": "1 pinch cinnamon"
        },
        {
          "ingredient_id": "e710b435-4dfe-43df-81a9-a025c79aa8c6",
          "input_qty": null,
          "input_unit_id": null,
          "is_optional": false,
          "note": null,
          "quantity_kind": "unquantified",
          "raw_text": "3/4 cups rice vinegar"
        },
        {
          "ingredient_id": "42c40cb2-bec7-4fbb-86bd-c9d80067b621",
          "input_qty": null,
          "input_unit_id": null,
          "is_optional": false,
          "note": null,
          "quantity_kind": "unquantified",
          "raw_text": "2/3 cups granulated sugar"
        },
        {
          "ingredient_id": "6cbd0052-817c-4b91-97ac-837db78b37df",
          "input_qty": null,
          "input_unit_id": null,
          "is_optional": false,
          "note": null,
          "quantity_kind": "unquantified",
          "raw_text": "1 bay leaf"
        },
        {
          "ingredient_id": "10de771c-3a45-4e50-ad76-fd2ee2d15c0d",
          "input_qty": null,
          "input_unit_id": null,
          "is_optional": false,
          "note": null,
          "quantity_kind": "unquantified",
          "raw_text": "METHOD"
        },
        {
          "ingredient_id": "6b42c4ec-8cd6-4b6b-b604-6baac07cbefe",
          "input_qty": null,
          "input_unit_id": null,
          "is_optional": false,
          "note": null,
          "quantity_kind": "unquantified",
          "raw_text": "Marinated Walnuts: In heatproof bowl, combine nuts, cocoa, lemon rind, pepper, allspice, cloves, Szechuan pepper (if using), vanilla, salt and cinnamon. In saucepan, bring vinegar, sugar and bay leaf to boil, stirring. Stir into nut mixture. Let cool; cover and let stand for at least 24 hours or for up to 3 days. Discard bay leaf."
        },
        {
          "ingredient_id": "8984ef21-970c-4944-8f2c-61b204889d4d",
          "input_qty": null,
          "input_unit_id": null,
          "is_optional": false,
          "note": null,
          "quantity_kind": "unquantified",
          "raw_text": "In saucepan over medium heat, melt butter; cook garlic and onion until golden, about 7 minutes. Stir in flour; cook, stirring, for 1 minute. Stir in wine; cook until reduced by half, about 1 minute. Stir in stock. Drain nuts, reserving liquid; add nuts to sauce along with 1/4 cup (50 mL) of the liquid. Bring to boil; reduce heat and simmer until slightly thickened, about 20 minutes. Set aside. (Make-ahead: Let cool. Cover and refrigerate for up to 1 day.)"
        },
        {
          "ingredient_id": "b116a1d1-9b77-466b-bd6e-709f7158f429",
          "input_qty": null,
          "input_unit_id": null,
          "is_optional": false,
          "note": null,
          "quantity_kind": "unquantified",
          "raw_text": "Meanwhile, season beef with salt and pepper. Place on greased rack in small roasting pan; roast in 450\u00b0F (230\u00b0C) oven until meat thermometer registers 130\u00b0 to 140\u00b0F (55\u00b0 to 60\u00b0C) for rare, 25 to 35 minutes. Tent with foil; let stand for 10 to 15 minutes. Bring sauce to simmer. Cut beef into 8 slices. Serve with walnut sauce."
        }
      ],
      "instruction": "See original recipe for details."
    }
  ]
}